LICENSE
MANIFEST.in
README-pypi.md
README.md
setup.cfg
setup.py
code_quality/.DS_Store
code_quality/__init__.py
code_quality/__main__.py
code_quality/advices.py
code_quality/comments_disitribution.py
code_quality/complete_check.py
code_quality/consistent_padding_line.py
code_quality/constants.py
code_quality/directory_score_aggr.py
code_quality/document_size.py
code_quality/function_size.py
code_quality/ideas.txt
code_quality/redundancy_check.py
code_quality/report.py
code_quality.egg-info/PKG-INFO
code_quality.egg-info/SOURCES.txt
code_quality.egg-info/dependency_links.txt
code_quality.egg-info/requires.txt
code_quality.egg-info/top_level.txt