Metadata-Version: 2.1
Name: code-quality
Version: 0.0.4
Summary: A light-weight library for testing code quality.
Home-page: https://github.com/ArthDubey/code_quality
Author: Arth Dubey
Author-email: arthdubey07@gmail.com
License: MIT
Download-URL: https://github.com/ArthDubey/code_quality/archive/v_01.gz
Keywords: test,quality,principles,linter,testing
Platform: UNKNOWN
Classifier: Intended Audience :: Developers
Classifier: License :: OSI Approved :: MIT License
Classifier: Programming Language :: Python :: 3
